flowpaths/__init__.py
flowpaths/__main__.py
flowpaths/abstractpathmodeldag.py
flowpaths/abstractsourcesinkgraph.py
flowpaths/abstractwalkmodeldigraph.py
flowpaths/kflowdecomp.py
flowpaths/kflowdecompcycles.py
flowpaths/kleastabserrors.py
flowpaths/kleastabserrorscycles.py
flowpaths/kminpatherror.py
flowpaths/kminpatherrorcycles.py
flowpaths/kpathcover.py
flowpaths/kpathcovercycles.py
flowpaths/minerrorflow.py
flowpaths/minflowdecomp.py
flowpaths/minflowdecompcycles.py
flowpaths/mingenset.py
flowpaths/minpathcover.py
flowpaths/minpathcovercycles.py
flowpaths/minsetcover.py
flowpaths/nodeexpandeddigraph.py
flowpaths/numpathsoptimization.py
flowpaths/stdag.py
flowpaths/stdigraph.py
flowpaths/utils/__init__.py
flowpaths/utils/dominators.py
flowpaths/utils/graphutils.py
flowpaths/utils/logging.py
flowpaths/utils/safetyflowdecomp.py
flowpaths/utils/safetypathcovers.py
flowpaths/utils/safetypathcoverscycles.py
flowpaths/utils/solverwrapper.py
flowpaths-0.2.11.dist-info/licenses/LICENSE
flowpaths-0.2.11.dist-info/METADATA
flowpaths-0.2.11.dist-info/WHEEL
flowpaths-0.2.11.dist-info/top_level.txt
flowpaths-0.2.11.dist-info/RECORD
