Metadata-Version: 2.4
Name: flowpaths
Version: 0.2.11
Summary: A Python package to quickly decompose weighted graphs into weights paths, under various models.
Author: Graph Algorithms and Bioinformatics Group @ University of Helsinki, and external collaborators
Project-URL: Homepage, https://github.com/algbio/flowpaths
Project-URL: Issues, https://github.com/algbio/flowpaths/issues
Project-URL: Documentation, https://algbio.github.io/flowpaths/
Classifier: Programming Language :: Python :: 3
Classifier: Operating System :: OS Independent
Classifier: License :: OSI Approved :: MIT License
Classifier: Topic :: Scientific/Engineering :: Bio-Informatics
Classifier: Topic :: Scientific/Engineering :: Information Analysis
Classifier: Topic :: Scientific/Engineering :: Mathematics
Classifier: Topic :: Software Development :: Libraries :: Python Modules
Classifier: Topic :: System :: Networking
Requires-Python: >=3.8
License-File: LICENSE
Requires-Dist: networkx
Requires-Dist: highspy
Requires-Dist: graphviz
Requires-Dist: numpy
Provides-Extra: dev
Requires-Dist: pytest>=8.0; extra == "dev"
Requires-Dist: pytest-cov>=5.0; extra == "dev"
Requires-Dist: pytest-xdist; extra == "dev"
Dynamic: license-file
